get_status_code/__init__.py
get_status_code/main.py
get_status_code_soreka-0.0.2.dist-info/LICENSE
get_status_code_soreka-0.0.2.dist-info/METADATA
get_status_code_soreka-0.0.2.dist-info/WHEEL
get_status_code_soreka-0.0.2.dist-info/top_level.txt
get_status_code_soreka-0.0.2.dist-info/RECORD
