Metadata-Version: 2.1
Name: get-status-code-soreka
Version: 0.0.2
Summary: test description
Home-page: https://github.com/pypa/sampleproject
Author: soreka
Author-email: rezafm1001@gmail.com
License: UNKNOWN
Project-URL: Bug Tracker, https://github.com/pypa/sampleproject/issues
Platform: UNKNOWN
Classifier: Programming Language :: Python :: 3
Classifier: License :: OSI Approved :: MIT License
Classifier: Operating System :: OS Independent
Requires-Python: >=3.6
License-File: LICENSE
Requires-Dist: requests
